gmail_client/__init__.py
gmail_client/api_client.py
gmail_client/configuration.py
gmail_client/rest.py
gmail_client/apis/__init__.py
gmail_client/apis/users_api.py
gmail_client/models/__init__.py
gmail_client/models/auto_forwarding.py
gmail_client/models/batch_delete_messages_request.py
gmail_client/models/batch_modify_messages_request.py
gmail_client/models/draft.py
gmail_client/models/filter.py
gmail_client/models/filter_action.py
gmail_client/models/filter_criteria.py
gmail_client/models/forwarding_address.py
gmail_client/models/history.py
gmail_client/models/history_label_added.py
gmail_client/models/history_label_removed.py
gmail_client/models/history_message_added.py
gmail_client/models/history_message_deleted.py
gmail_client/models/imap_settings.py
gmail_client/models/label.py
gmail_client/models/list_drafts_response.py
gmail_client/models/list_filters_response.py
gmail_client/models/list_forwarding_addresses_response.py
gmail_client/models/list_history_response.py
gmail_client/models/list_labels_response.py
gmail_client/models/list_messages_response.py
gmail_client/models/list_send_as_response.py
gmail_client/models/list_smime_info_response.py
gmail_client/models/list_threads_response.py
gmail_client/models/message.py
gmail_client/models/message_part.py
gmail_client/models/message_part_body.py
gmail_client/models/message_part_header.py
gmail_client/models/modify_message_request.py
gmail_client/models/modify_thread_request.py
gmail_client/models/pop_settings.py
gmail_client/models/profile.py
gmail_client/models/send_as.py
gmail_client/models/smime_info.py
gmail_client/models/smtp_msa.py
gmail_client/models/thread.py
gmail_client/models/vacation_settings.py
gmail_client/models/watch_request.py
gmail_client/models/watch_response.py
swagger_gmail_client-1.0.1.dist-info/DESCRIPTION.rst
swagger_gmail_client-1.0.1.dist-info/METADATA
swagger_gmail_client-1.0.1.dist-info/RECORD
swagger_gmail_client-1.0.1.dist-info/WHEEL
swagger_gmail_client-1.0.1.dist-info/metadata.json
swagger_gmail_client-1.0.1.dist-info/top_level.txt
test/__init__.py
test/test_auto_forwarding.py
test/test_batch_delete_messages_request.py
test/test_batch_modify_messages_request.py
test/test_draft.py
test/test_filter.py
