Metadata-Version: 2.0
Name: swagger-gmail-client
Version: 1.0.1
Summary: A Swagger generated client for the Gmail v1 API
Home-page: https://github.com/CanopyIQ/gmail_client
Author: Samiur Rahman
Author-email: samiur@canopyiq.com
License: UNKNOWN
Keywords: Swagger,Gmail
Platform: UNKNOWN
Classifier: Development Status :: 5 - Production/Stable
Classifier: Intended Audience :: Developers
Classifier: Natural Language :: English
Classifier: License :: OSI Approved :: MIT License
Classifier: Programming Language :: Python
Classifier: Programming Language :: Python :: 2.7
Classifier: Programming Language :: Python :: 3
Classifier: Programming Language :: Python :: 3.3
Classifier: Programming Language :: Python :: 3.4
Classifier: Programming Language :: Python :: 3.5
Requires-Dist: certifi
Requires-Dist: python-dateutil
Requires-Dist: six (>=1.10)
Requires-Dist: urllib3 (>=1.15)
